MANIFEST.in
README.md
setup.py
ibm_cloud_env/IBMCloudEnv.py
ibm_cloud_env/__init__.py
ibm_cloud_env.egg-info/PKG-INFO
ibm_cloud_env.egg-info/SOURCES.txt
ibm_cloud_env.egg-info/dependency_links.txt
ibm_cloud_env.egg-info/not-zip-safe
ibm_cloud_env.egg-info/requires.txt
ibm_cloud_env.egg-info/top_level.txt
test/test_IBMCloudEnv.py
test/cases/test-file-json-object.json
test/cases/test-file-plain-text.txt