Metadata-Version: 1.1
Name: ibm-cloud-env
Version: 0.0.4
Summary: Abstraction layer for CF and Kube env variables
Home-page: http://github.ibm.com/Liz-Furlan/ibm_cloud_env
Author: Liz Furlan
Author-email: Liz-Furlan@ibm.com
License: Apache-2.0
Keywords: ibm,cloud,cloud foundry,environment variable,kubernetes
Platform: UNKNOWN
Classifier: Programming Language :: Python :: 2.6
Classifier: Programming Language :: Python :: 2.7
Classifier: Programming Language :: Python :: 3.3
Classifier: Programming Language :: Python :: 3.4
Classifier: Programming Language :: Python :: 3.5
Classifier: Programming Language :: Python :: 3.6
